first_package/__init__.py
first_package/simple_fn.py
first_package/simple_fn2.py
first_package_gc1-0.2.dist-info/LICENSE
first_package_gc1-0.2.dist-info/METADATA
first_package_gc1-0.2.dist-info/WHEEL
first_package_gc1-0.2.dist-info/top_level.txt
first_package_gc1-0.2.dist-info/RECORD
