Metadata-Version: 2.1
Name: first-package-gc1
Version: 0.2
Summary: testing first package to pypi
Home-page: https://github.com/gcow/first_package
Author: garyc
Author-email: gary.cowlam@gmail.com
License: UNKNOWN
Platform: UNKNOWN
Requires-Dist: numpy
Requires-Dist: DateTime
